scalabel/__init__.py
scalabel/py.typed
scalabel/bot/__init__.py
scalabel/bot/polyrnn_adapter.py
scalabel/bot/seg_base.py
scalabel/bot/seg_dummy.py
scalabel/common/__init__.py
scalabel/common/io.py
scalabel/common/logger.py
scalabel/common/parallel.py
scalabel/common/quiet.py
scalabel/common/tqdm.py
scalabel/common/typing.py
scalabel/eval/__init__.py
scalabel/eval/boundary.py
scalabel/eval/detect.py
scalabel/eval/ins_seg.py
scalabel/eval/mot.py
scalabel/eval/mots.py
scalabel/eval/pan_seg.py
scalabel/eval/pose.py
scalabel/eval/result.py
scalabel/eval/sem_seg.py
scalabel/eval/tagging.py
scalabel/eval/utils.py
scalabel/label/__init__.py
scalabel/label/coco_typing.py
scalabel/label/from_coco.py
scalabel/label/from_crowdhuman.py
scalabel/label/from_kitti.py
scalabel/label/from_mot.py
scalabel/label/from_nuscenes.py
scalabel/label/from_waymo.py
scalabel/label/io.py
scalabel/label/kitti_utlis.py
scalabel/label/test_utils.py
scalabel/label/to_coco.py
scalabel/label/to_nuscenes.py
scalabel/label/to_rle.py
scalabel/label/transforms.py
scalabel/label/typing.py
scalabel/label/utils.py
scalabel/tools/__init__.py
scalabel/tools/detect_ground.py
scalabel/tools/edit_labels.py
scalabel/tools/launch_server.py
scalabel/tools/prepare_data.py
scalabel/vis/__init__.py
scalabel/vis/controller.py
scalabel/vis/geometry.py
scalabel/vis/helper.py
scalabel/vis/label.py
tests/__init__.py
tests/util.py
tests/common/__init__.py
tests/common/io_test.py
tests/common/parallel_test.py
tests/eval/__init__.py
tests/eval/boundary_test.py
tests/eval/detect_test.py
tests/eval/ins_seg_test.py
tests/eval/mot_test.py
tests/eval/mots_test.py
tests/eval/pan_seg_test.py
tests/eval/pose_test.py
tests/eval/result_test.py
tests/eval/sem_seg_test.py
tests/eval/tagging_test.py
tests/eval/utils_test.py
tests/label/__init__.py
tests/label/from_coco_test.py
tests/label/from_kitti_test.py
tests/label/from_mot_test.py
tests/label/from_waymo_test.py
tests/label/io_test.py
tests/label/to_coco_test.py
scalabel-0.3.1.dist-info/LICENSE
scalabel-0.3.1.dist-info/METADATA
scalabel-0.3.1.dist-info/WHEEL
scalabel-0.3.1.dist-info/top_level.txt
scalabel-0.3.1.dist-info/RECORD
