Metadata-Version: 2.1
Name: scalabel
Version: 0.3.1
Summary: Scalabel Python Package
Home-page: https://scalabel.ai/
Author: Fisher Yu
Author-email: i@yf.io
Project-URL: Documentation, https://doc.scalabel.ai
Project-URL: Source, https://github.com/scalabel/scalabel
Project-URL: Tracker, https://github.com/scalabel/scalabel/issues
Classifier: Programming Language :: Python :: 3.7
Classifier: Programming Language :: Python :: 3.8
Classifier: Programming Language :: Python :: 3.9
Classifier: Programming Language :: Python :: 3.10
Classifier: License :: OSI Approved :: Apache Software License
Classifier: Operating System :: OS Independent
Requires-Python: >=3.7
License-File: LICENSE
Requires-Dist: boto3
Requires-Dist: joblib
Requires-Dist: matplotlib
Requires-Dist: motmetrics
Requires-Dist: nanoid
Requires-Dist: numpy
Requires-Dist: pandas
Requires-Dist: Pillow
Requires-Dist: plyfile
Requires-Dist: psutil
Requires-Dist: pycocotools
Requires-Dist: pydantic
Requires-Dist: pyparsing
Requires-Dist: python-dateutil
Requires-Dist: PyYAML
Requires-Dist: requests
Requires-Dist: scikit-image
Requires-Dist: tabulate
Requires-Dist: tqdm
Requires-Dist: toml
